django_date_extensions/__init__.py
django_date_extensions/fields.py
django_date_extensions/models.py
django_date_extensions/settings.py
django_date_extensions/tests.py
django_date_extensions/widgets.py
django_date_extensions-3.1.2.dist-info/LICENSE.txt
django_date_extensions-3.1.2.dist-info/METADATA
django_date_extensions-3.1.2.dist-info/WHEEL
django_date_extensions-3.1.2.dist-info/top_level.txt
django_date_extensions-3.1.2.dist-info/RECORD
