Metadata-Version: 2.1
Name: django-date-extensions
Version: 3.1.2
Summary: This code adds a few small extensions to Django's DateField,to handle both approximate dates (e.g. 'March 1963') and default year dates(e.g. assume '24th June' is the most recent such).
Home-page: https://github.com/dracos/django-date-extensions
Author: Matthew Somerville
Author-email: matthew-pypi@dracos.co.uk
License: BSD
Platform: UNKNOWN
Classifier: Development Status :: 5 - Production/Stable
Classifier: Environment :: Web Environment
Classifier: Framework :: Django
Classifier: License :: OSI Approved :: BSD License
Classifier: Intended Audience :: Developers
Classifier: Programming Language :: Python :: 2.7
Classifier: Programming Language :: Python :: 3
Classifier: Topic :: Database
Classifier: Topic :: Internet :: WWW/HTTP
Requires: Django
